projectile/__init__.py
projectile/_version.py
projectile/client.html
projectile/get_test_data.py
projectile/image_to_array.py
projectile/server.py
projectile-0.0.6.dist-info/METADATA
projectile-0.0.6.dist-info/WHEEL
projectile-0.0.6.dist-info/entry_points.txt
projectile-0.0.6.dist-info/top_level.txt
projectile-0.0.6.dist-info/RECORD
