Metadata-Version: 2.1
Name: projectile
Version: 0.0.6
Summary: A tile-on-demand tile server built with PIL and Tornado
Home-page: https://github.com/sclabs/projectile
Author: Thomas Gilgenast
Author-email: thomasgilgenast@gmail.com
License: UNKNOWN
Keywords: tileserver tile server on-demand tiling
Platform: UNKNOWN
Classifier: Development Status :: 3 - Alpha
Classifier: Environment :: Console
Classifier: Intended Audience :: Developers
Classifier: Intended Audience :: Science/Research
Classifier: Programming Language :: Python :: 2
Classifier: Programming Language :: Python :: 2.7
Classifier: Programming Language :: Python :: 3
Classifier: Programming Language :: Python :: 3.6
Classifier: Operating System :: OS Independent
Classifier: Topic :: Multimedia :: Graphics :: Viewers
Classifier: Topic :: Scientific/Engineering :: Visualization
Requires-Dist: numpy (>=1.13.3)
Requires-Dist: Pillow (>=4.3.0)
Requires-Dist: tornado (>=4.5.2)
Requires-Dist: six (>=1.11.0)
Requires-Dist: matplotlib (>=2.1.1)
